manim_json/__init__.py
manim_json/json_camera.py
manim_json/json_renderer.py
manim_json/json_scene.py
manim_json-0.2.0.dist-info/METADATA
manim_json-0.2.0.dist-info/WHEEL
manim_json-0.2.0.dist-info/RECORD
