Metadata-Version: 2.1
Name: manim-json
Version: 0.2.0
Summary: 
Author: MathItYT
Author-email: benjamin.ubilla@uc.cl
Requires-Python: >=3.9,<3.13
Classifier: Programming Language :: Python :: 3
Classifier: Programming Language :: Python :: 3.9
Classifier: Programming Language :: Python :: 3.10
Classifier: Programming Language :: Python :: 3.11
Classifier: Programming Language :: Python :: 3.12
Requires-Dist: manim (>=0.18.1,<0.19.0)
